vnpy_leveldb/__init__.py
vnpy_leveldb/leveldb_database.py
vnpy_leveldb-1.0.3.dist-info/LICENSE
vnpy_leveldb-1.0.3.dist-info/METADATA
vnpy_leveldb-1.0.3.dist-info/WHEEL
vnpy_leveldb-1.0.3.dist-info/top_level.txt
vnpy_leveldb-1.0.3.dist-info/RECORD
